{
    "pages": {
        "mission": {
            "title": "משימה"
        },
        "exchange": {
            "title": "החלפות",
            "message_title": "בשביל 10% הנחה",
            "message_content": "שילחו סיפור, או שיר, או כל צורה אחרת של חיבור מילים, בתמורה ל 10% הנחה.",
            "text_direction": "כיוון כתיבה:",
            "input_name_placeholder": "*שם",
            "input_email_placeholder": "*example@mail.com",
            "input_message_placeholder": "לכתוב כאן...",
            "disclamer_message": "בשליחה אני מסכים ש Ms-Sugar תעשה שימוש מסחרי במילים שכתבתי.",
            "read_more": "למידע נוסף ",
            "read_more_link": "כנסו לעמוד התנאים.",
            "i_agree": "אני מסכים",
            "submit": "שליחה"
        },
        "product": {
            "share":{
                "title": "שיתוף:",
                "options": {
                    "copy": "העתק",
                    "x": "אקס",
                    "whatsapp": "ווצאפ",
                    "facebook": "פיסבוק",
                    "messenger": "מסנגר",
                    "gmail": "גימייל",
                    "telegram": "טלגרם"
                }
            },
            "back_to_skateshop": {
                "title": "חזרה לחנות"
            },
            "quantity": {
                "title": "כמות:"
            },
            "in_stock": {
                "title": "יש במלאי"
            },
            "out_of_stock": {
                "title": "אין במלאי"
            },
            "shipping": {
                "title": "משלוח:"
            },
            "variant": {
                "title": "מפרט:"
            },
            "add_to_cart_button": {
                "title": "להוסיף לעגלה"
            },
            "cart_button": {
                "title": "עגלה"
            },
            "notify_button": {
                "title": "תנו לי התראה כשהמוצר יהיה זמין"
            },
            "notify_popup": {
                "message_top": "קבלו התראה כשהמוצר יחזור למלאי. לפעמים הם נגמרים מהר, ככה תהיו הראשונים לדעת.",
                "message_bottom": "הרשמה זו תשמש להתראה עבור זמינות שמוצר בלבד.",
                "submit_button": {
                    "title": "שליחה"
                }
            },
            "related_products": {
                "title": "מוצרים נוספים:"
            }
        },
        "skateshop": {
            "title": "חנות",
            "products": {
                "list": {
                    "deck_#1": {
                        "title": "קרש #1",
                        "description_html": "<p><span>Lorem ipsum dolor sit amet, consectetur adipiscing elit, sed do eiusmod tempor incididunt ut labore et dolore magna aliqua. Ut enim ad minim veniam, quis nostrud exercitation ullamco laboris nisi ut aliquip ex ea commodo consequat. Duis aute irure dolor in reprehenderit in voluptate velit esse cillum dolore eu fugiat nulla pariatur. Excepteur sint occaecat cupidatat non proident, sunt in culpa qui officia deserunt mollit anim id est laborum.</span></p>"
                    },
                    "deck_#2": {
                        "title": "קרש #2",
                        "description_html": "<p><span>Lorem ipsum dolor sit amet, consectetur adipiscing elit, sed do eiusmod tempor incididunt ut labore et dolore magna aliqua. Ut enim ad minim veniam, quis nostrud exercitation ullamco laboris nisi ut aliquip ex ea commodo consequat. Duis aute irure dolor in reprehenderit in voluptate velit esse cillum dolore eu fugiat nulla pariatur. Excepteur sint occaecat cupidatat non proident, sunt in culpa qui officia deserunt mollit anim id est laborum.</span></p>"
                    },
                    "deck_#3": {
                        "title": "קרש #3",
                        "description_html": "<p><span>לורם איפסום דולור סיט אמט, קונסקטetur אדיפיסינג אליט, סד דו איאוסמוד טמפור אינצידידונט אוט לבורה אט דולור מגנה אליקווה. אוט אנים עד מינימום וניאם, קוויס נוסטרוד אקסרציטציה אוללאמקו לבוריס ניסי אוט אליקויפ אקס אה קוממודו קונסקוואט. דואיס אוטה אירורה דולור אין רהפריהנדריט אין וולופטאטה ווליט אסה ציליום דולור אהו פוגיט נוללה פאריאטור. אקסצפטר סינט אוקאיקאט קופידאטאט נון פרוידנט, סונט אין קולפה קווי אופיסיה דזרונט מוליט אנים איד אסט לאבורום.</span></p>"
                    },
                    "wheels": {
                        "title": "גלגלים",
                        "description_html": "<p><span>לורם איפסום דולור סיט אמט, קונסקטetur אדיפיסינג אליט, סד דו איאוסמוד טמפור אינצידידונט אוט לבורה אט דולור מגנה אליקווה. אוט אנים עד מינימום וניאם, קוויס נוסטרוד אקסרציטציה אוללאמקו לבוריס ניסי אוט אליקויפ אקס אה קוממודו קונסקוואט. דואיס אוטה אירורה דולור אין רהפריהנדריט אין וולופטאטה ווליט אסה ציליום דולור אהו פוגיט נוללה פאריאטור. אקסצפטר סינט אוקאיקאט קופידאטאט נון פרוידנט, סונט אין קולפה קווי אופיסיה דזרונט מוליט אנים איד אסט לאבורום.</span></p>"
                    },
                    "bearings": {
                        "title": "מייסבים",
                        "description_html": "<p><span>לורם איפסום דולור סיט אמט, קונסקטetur אדיפיסינג אליט, סד דו איאוסמוד טמפור אינצידידונט אוט לבורה אט דולור מגנה אליקווה. אוט אנים עד מינימום וניאם, קוויס נוסטרוד אקסרציטציה אוללאמקו לבוריס ניסי אוט אליקויפ אקס אה קוממודו קונסקוואט. דואיס אוטה אירורה דולור אין רהפריהנדריט אין וולופטאטה ווליט אסה ציליום דולור אהו פוגיט נוללה פאריאטור. אקסצפטר סינט אוקאיקאט קופידאטאט נון פרוידנט, סונט אין קולפה קווי אופיסיה דזרונט מוליט אנים איד אסט לאבורום.</span></p>"
                    },
                    "grip": {
                        "title": "גריפ",
                        "description_html": "<p><span>לורם איפסום דולור סיט אמט, קונסקטetur אדיפיסינג אליט, סד דו איאוסמוד טמפור אינצידידונט אוט לבורה אט דולור מגנה אליקווה. אוט אנים עד מינימום וניאם, קוויס נוסטרוד אקסרציטציה אוללאמקו לבוריס ניסי אוט אליקויפ אקס אה קוממודו קונסקוואט. דואיס אוטה אירורה דולור אין רהפריהנדריט אין וולופטאטה ווליט אסה ציליום דולור אהו פוגיט נוללה פאריאטור. אקסצפטר סינט אוקאיקאט קופידאטאט נון פרוידנט, סונט אין קולפה קווי אופיסיה דזרונט מוליט אנים איד אסט לאבורום.</span></p>"
                    }
                },
                "collections": {
                    "all_products": "כל המוצרים",
                    "decks": "קרשים",
                    "wheels": "גלגלים",
                    "bearings": "מייסבים",
                    "grips": "גריפים"
                },
                "no_filters_message": "אין פילטרים לקטגוריה:",
                "options": {
                    "color": {
                        "title": "צבע",
                        "values": {
                            "black": "שחור",
                            "white": "לבן"
                        }
                    },
                    "bearings_balls": {
                        "title": "כדורים",
                        "values": {
                            "chrome": "כרום"
                        }
                    },
                    "abec": {
                        "title": "גימור (Abec)",
                        "values": {
                            "7": "7"
                        }
                    },
                    "deck_size": {
                        "title": "מידה",
                        "values": {
                            "8": "8\""
                        }
                    },
                    "concave": {
                        "title": "גובה צד (Concave)",
                        "values": {
                            "medium": "בינוני"
                        }
                    },
                    "grip_roughness": {
                        "title": "חיספוס",
                        "values": {
                            "medium_780": "בינוני (780)"
                        }
                    },
                    "grip_size": {
                        "title": "מידות",
                        "values": {
                            "9_33": "9\" * 33\""
                        }
                    },
                    "wheels_material": {
                        "title": "חומר",
                        "values": {
                            "101A": "101A"
                        }
                    },
                    "wheels_size": {
                        "title": "מידות",
                        "values": {
                            "54_34_mm": "34 * 54"
                        }
                    }
                }
            }
        },
        "cart": {
            "title": "עגלה",
            "your_cart_is_empty": "העגלה ריקה",
            "go_to": "חזרה לעמוד",
            "skateshop": "חנות",
            "sub_total_title": "סכום ביניים:",
            "shipping_title": "משלוח:",
            "shipping_message_with_no_country": "עלות המשלוח מחושבת לפי הכתובת בעת התשלום.",
            "shipping_message_with_country": "משלוחים חינם ב{country} להזמנות מעל {shippingThreshold}. העלות מחושבת לפי הכתובת בעת התשלום.",
            "tax_title": "מיסים:",
            "tax_message": "מיסים מחושבים לפי הכתובת בעת התשלום.",
            "discount_title": "קופונים:",
            "discount_message": "ניתן להוסיף קופון הנחה בעת התשלום.",
            "checkout": "לתשלום",
            "delete_message": "הפריט ימחק מהעגלה.",
            "delete_confirm": "אישור",
            "delete_abort": "ביטול"
        },
        "contact": {
            "title": "קשר",
            "message_title": "ספרו הכל",
            "message_placeholder": "לכתוב כאן...",
            "submit": "שליחה"
        },
        "faq": {
            "title": "תשובות",
            "search_placeholder": "שאלות...",
            "all": "הכל"
        },
        "privacy": {
            "title": "פרטיות"
        },
        "terms": {
            "title": "תנאים",
            "section_main_title": "תנאים",
            "last_update": "עדכון אחרון:"
        }
    },
    "footer": {
        "social": {
            "title": "רשת",
            "twitter": {
                "title": "טוויטר"
            }
        },
        "legal": {
            "title": "חוקים"
        },
        "market": {
            "title": "שוק"
        },
        "info": {
            "title": "מידע"
        },
        "copyright": {
            "line_one": "© Ms-Sugar | כל הזכויות שמורות"
        },
        "built_with_love": {
            "title": "נבנה באהבה"
        }
    }
}